utilityhub_config/__init__.py
utilityhub_config/api.py
utilityhub_config/errors.py
utilityhub_config/metadata.py
utilityhub_config/readers/__init__.py
utilityhub_config/readers/dotenv_reader.py
utilityhub_config/readers/toml_reader.py
utilityhub_config/readers/yaml_reader.py
utilityhub_config/resolver.py
utilityhub_config-0.2.1.dist-info/WHEEL
utilityhub_config-0.2.1.dist-info/entry_points.txt
utilityhub_config-0.2.1.dist-info/METADATA
utilityhub_config-0.2.1.dist-info/RECORD
