Metadata-Version: 2.3
Name: utilityhub_config
Version: 0.2.1
Summary: A deterministic, typed configuration engine for serious automation systems
Author: Rajesh Das
Author-email: Rajesh Das <rajesh@hyperoot.dev>
Requires-Dist: pydantic>=2.12.5
Requires-Dist: pyyaml>=6.0.3
Requires-Dist: python-dotenv>=1.2.1
Requires-Python: >=3.12
